solid2_extensions/BOSL/__init__.py
solid2_extensions/BOSL/acme_screws.py
solid2_extensions/BOSL/beziers.py
solid2_extensions/BOSL/compat.py
solid2_extensions/BOSL/constants.py
solid2_extensions/BOSL/convex_hull.py
solid2_extensions/BOSL/debug.py
solid2_extensions/BOSL/examples/__init__.py
solid2_extensions/BOSL/examples/bezier_patches.py
solid2_extensions/BOSL/examples/orientations.py
solid2_extensions/BOSL/involute_gears.py
solid2_extensions/BOSL/joiners.py
solid2_extensions/BOSL/linear_bearings.py
solid2_extensions/BOSL/masks.py
solid2_extensions/BOSL/math.py
solid2_extensions/BOSL/metric_screws.py
solid2_extensions/BOSL/nema_steppers.py
solid2_extensions/BOSL/paths.py
solid2_extensions/BOSL/phillips_drive.py
solid2_extensions/BOSL/quaternions.py
solid2_extensions/BOSL/shapes.py
solid2_extensions/BOSL/sliders.py
solid2_extensions/BOSL/tests/__init__.py
solid2_extensions/BOSL/tests/test_convex_hull.py
solid2_extensions/BOSL/tests/test_math.py
solid2_extensions/BOSL/threading.py
solid2_extensions/BOSL/torx_drive.py
solid2_extensions/BOSL/transforms.py
solid2_extensions/BOSL/triangulation.py
solid2_extensions/BOSL/wiring.py
solid2_extensions/BOSL2/__init__.py
solid2_extensions/BOSL2/affine.py
solid2_extensions/BOSL2/attachments.py
solid2_extensions/BOSL2/beziers.py
solid2_extensions/BOSL2/bosl1compat.py
solid2_extensions/BOSL2/bottlecaps.py
solid2_extensions/BOSL2/builtins.py
solid2_extensions/BOSL2/color.py
solid2_extensions/BOSL2/comparisons.py
solid2_extensions/BOSL2/constants.py
solid2_extensions/BOSL2/coords.py
solid2_extensions/BOSL2/cubetruss.py
solid2_extensions/BOSL2/distributors.py
solid2_extensions/BOSL2/drawing.py
solid2_extensions/BOSL2/fnliterals.py
solid2_extensions/BOSL2/gears.py
solid2_extensions/BOSL2/geometry.py
solid2_extensions/BOSL2/hingesnaps.py
solid2_extensions/BOSL2/joiners.py
solid2_extensions/BOSL2/linalg.py
solid2_extensions/BOSL2/linear_bearings.py
solid2_extensions/BOSL2/lists.py
solid2_extensions/BOSL2/masks2d.py
solidpython2_extensions-0.1.4.dist-info/METADATA
solidpython2_extensions-0.1.4.dist-info/WHEEL
solidpython2_extensions-0.1.4.dist-info/RECORD
