Metadata-Version: 2.1
Name: solidpython2-extensions
Version: 0.1.4
Summary: some extensions for solidpython2
License: LGPL
Author: jeff
Author-email: 1105041+jeff-dh@users.noreply.github.com
Requires-Python: >=3.8,<4.0
Classifier: License :: Other/Proprietary License
Classifier: Programming Language :: Python :: 3
Classifier: Programming Language :: Python :: 3.8
Classifier: Programming Language :: Python :: 3.9
Classifier: Programming Language :: Python :: 3.10
Classifier: Programming Language :: Python :: 3.11
Requires-Dist: solidpython2 (>=2.0.0-beta.3,<3.0.0)
